attackerkb_api/__init__.py
attackerkb_api/api.py
attackerkb_api-0.0.8.dist-info/METADATA
attackerkb_api-0.0.8.dist-info/WHEEL
attackerkb_api-0.0.8.dist-info/licenses/LICENSE
attackerkb_api-0.0.8.dist-info/RECORD
