Metadata-Version: 2.4
Name: attackerkb-api
Version: 0.0.8
Summary: AttackerKB API Library
Project-URL: Homepage, https://github.com/kevthehermit/attackerkb-api
Project-URL: Repository, https://github.com/kevthehermit/attackerkb-api
Author-email: Kev Breen <kevin@techanarchy.net>
License-Expression: MIT
License-File: LICENSE
Classifier: License :: OSI Approved :: MIT License
Classifier: Operating System :: OS Independent
Classifier: Programming Language :: Python :: 3
Classifier: Programming Language :: Python :: 3.10
Classifier: Programming Language :: Python :: 3.11
Classifier: Programming Language :: Python :: 3.12
Requires-Python: >=3.10
Requires-Dist: requests>=2.25.0
Provides-Extra: mcp
Requires-Dist: fastmcp>=0.1.0; extra == 'mcp'
